omero_cli_render.py
omero/plugins/render.py
omero_cli_render-0.8.1.dist-info/LICENSE.txt
omero_cli_render-0.8.1.dist-info/METADATA
omero_cli_render-0.8.1.dist-info/WHEEL
omero_cli_render-0.8.1.dist-info/top_level.txt
omero_cli_render-0.8.1.dist-info/RECORD
