Metadata-Version: 2.1
Name: omero-cli-render
Version: 0.8.1
Summary: Plugin for use in the OMERO CLI.
Home-page: https://github.com/ome/omero-cli-render/
Author: The Open Microscopy Team
Author-email: ome-devel@lists.openmicroscopy.org.uk
License: GPL-2.0+
Download-URL: https://github.com/ome/omero-cli-render//v0.8.1.tar.gz
Keywords: OMERO.CLI,plugin
Platform: UNKNOWN
Classifier: Development Status :: 5 - Production/Stable
Classifier: Environment :: Plugins
Classifier: Intended Audience :: Developers
Classifier: Intended Audience :: End Users/Desktop
Classifier: License :: OSI Approved :: GNU General Public License v2 or later (GPLv2+)
Classifier: Natural Language :: English
Classifier: Operating System :: OS Independent
Classifier: Programming Language :: Python :: 3
Classifier: Topic :: Software Development :: Libraries :: Python Modules
Requires-Python: >=3.8
License-File: LICENSE.txt
Requires-Dist: PyYAML
Requires-Dist: omero-py (>=5.6.0)
